{
    "dea":
    {},
    "adjacency":
    {
        "46":
        {
            "47": null
        },
        "16":
        {
            "17": null
        },
        "36":
        {
            "37": null
        },
        "26":
        {
            "27": null
        },
        "45":
        {
            "44": null
        },
        "48":
        {
            "49": null
        },
        "15":
        {
            "14": null
        },
        "18":
        {
            "19": null
        },
        "35":
        {
            "34": null
        },
        "25":
        {
            "24": null
        },
        "28":
        {
            "29": null
        },
        "38":
        {
            "39": null
        },
        "40":
        {
            "41": null
        },
        "50":
        {
            "51": null
        },
        "10":
        {
            "11": null
        },
        "30":
        {
            "31": null
        },
        "20":
        {
            "21": null
        },
        "47":
        {
            "46": null
        },
        "17":
        {
            "16": null
        },
        "37":
        {
            "36": null
        },
        "27":
        {
            "26": null
        },
        "52":
        {
            "53": null
        },
        "42":
        {
            "43": null
        },
        "12":
        {
            "13": null
        },
        "32":
        {
            "33": null
        },
        "22":
        {
            "23": null
        },
        "49":
        {
            "48": null
        },
        "19":
        {
            "18": null
        },
        "39":
        {
            "38": null
        },
        "29":
        {
            "28": null
        },
        "51":
        {
            "50": null
        },
        "41":
        {
            "40": null
        },
        "11":
        {
            "10": null
        },
        "5":
        {
            "4": null
        },
        "4":
        {
            "5": null
        },
        "7":
        {
            "6": null
        },
        "6":
        {
            "7": null
        },
        "1":
        {
            "0": null
        },
        "0":
        {
            "1": null
        },
        "3":
        {
            "2": null
        },
        "2":
        {
            "3": null
        },
        "21":
        {
            "20": null
        },
        "31":
        {
            "30": null
        },
        "9":
        {
            "8": null
        },
        "8":
        {
            "9": null
        },
        "44":
        {
            "45": null
        },
        "14":
        {
            "15": null
        },
        "34":
        {
            "35": null
        },
        "24":
        {
            "25": null
        },
        "53":
        {
            "52": null
        },
        "43":
        {
            "42": null
        },
        "13":
        {
            "12": null
        },
        "33":
        {
            "32": null
        },
        "23":
        {
            "22": null
        }
    },
    "node":
    {
        "46":
        {
            "z": 61.786270261047889,
            "y": 0.0,
            "x": 15.110032640734133
        },
        "16":
        {
            "z": 0.0,
            "y": 0.0,
            "x": 0.0
        },
        "36":
        {
            "z": 32.933735708960668,
            "y": 0.0,
            "x": -23.953339987207471
        },
        "26":
        {
            "z": 0.0,
            "y": 0.0,
            "x": 0.0
        },
        "45":
        {
            "z": 61.786270261047889,
            "y": 0.0,
            "x": 15.110032640734133
        },
        "48":
        {
            "z": 48.053014536037871,
            "y": 0.0,
            "x": 19.817490439258414
        },
        "15":
        {
            "z": 61.786270261047889,
            "y": 0.0,
            "x": -15.110032640734133
        },
        "18":
        {
            "z": 0.0,
            "y": 0.0,
            "x": -10.371174563393762
        },
        "35":
        {
            "z": 32.933735708960668,
            "y": 0.0,
            "x": -23.953339987207471
        },
        "25":
        {
            "z": 61.786270261047889,
            "y": 0.0,
            "x": 15.110032640734133
        },
        "28":
        {
            "z": 0.0,
            "y": 0.0,
            "x": 10.371174563393762
        },
        "38":
        {
            "z": 48.053014536037871,
            "y": 0.0,
            "x": -19.817490439258414
        },
        "40":
        {
            "z": 61.786270261047889,
            "y": 0.0,
            "x": -15.110032640734133
        },
        "50":
        {
            "z": 32.933735708960668,
            "y": 0.0,
            "x": 23.953339987207471
        },
        "10":
        {
            "z": 0.0,
            "y": 0.0,
            "x": 20.74234912678752
        },
        "30":
        {
            "z": 0.0,
            "y": 0.0,
            "x": 20.74234912678752
        },
        "20":
        {
            "z": 0.0,
            "y": 0.0,
            "x": -20.742349126787527
        },
        "47":
        {
            "z": 48.053014536037871,
            "y": 0.0,
            "x": 19.817490439258414
        },
        "17":
        {
            "z": 48.053014536037871,
            "y": 0.0,
            "x": -19.817490439258414
        },
        "37":
        {
            "z": 48.053014536037871,
            "y": 0.0,
            "x": -19.817490439258414
        },
        "27":
        {
            "z": 48.053014536037871,
            "y": 0.0,
            "x": 19.817490439258414
        },
        "52":
        {
            "z": 16.835727419499008,
            "y": 0.0,
            "x": 27.685552802878718
        },
        "42":
        {
            "z": 73.323294005470174,
            "y": 0.0,
            "x": -9.4968292464773363
        },
        "12":
        {
            "z": 0.0,
            "y": 0.0,
            "x": 20.74234912678752
        },
        "32":
        {
            "z": 0.0,
            "y": 0.0,
            "x": -31.113523690181285
        },
        "22":
        {
            "z": 0.0,
            "y": 0.0,
            "x": -20.742349126787527
        },
        "49":
        {
            "z": 32.933735708960668,
            "y": 0.0,
            "x": 23.953339987207471
        },
        "19":
        {
            "z": 32.933735708960668,
            "y": 0.0,
            "x": -23.953339987207471
        },
        "39":
        {
            "z": 61.786270261047889,
            "y": 0.0,
            "x": -15.110032640734133
        },
        "29":
        {
            "z": 32.933735708960668,
            "y": 0.0,
            "x": 23.953339987207471
        },
        "51":
        {
            "z": 16.835727419499008,
            "y": 0.0,
            "x": 27.685552802878718
        },
        "41":
        {
            "z": 73.323294005470174,
            "y": 0.0,
            "x": -9.4968292464773363
        },
        "11":
        {
            "z": 0.0,
            "y": 0.0,
            "x": 31.113523690181285
        },
        "5":
        {
            "z": 0.0,
            "y": 0.0,
            "x": 0.0
        },
        "4":
        {
            "z": 0.0,
            "y": 0.0,
            "x": -10.371174563393762
        },
        "7":
        {
            "z": 0.0,
            "y": 0.0,
            "x": 10.371174563393762
        },
        "6":
        {
            "z": 0.0,
            "y": 0.0,
            "x": 0.0
        },
        "1":
        {
            "z": 0.0,
            "y": 0.0,
            "x": -20.742349126787527
        },
        "0":
        {
            "z": 0.0,
            "y": 0.0,
            "x": -31.113523690181285
        },
        "3":
        {
            "z": 0.0,
            "y": 0.0,
            "x": -10.371174563393762
        },
        "2":
        {
            "z": 0.0,
            "y": 0.0,
            "x": -20.742349126787527
        },
        "21":
        {
            "z": 16.835727419499008,
            "y": 0.0,
            "x": -27.685552802878718
        },
        "31":
        {
            "z": 16.835727419499008,
            "y": 0.0,
            "x": 27.685552802878718
        },
        "9":
        {
            "z": 0.0,
            "y": 0.0,
            "x": 20.74234912678752
        },
        "8":
        {
            "z": 0.0,
            "y": 0.0,
            "x": 10.371174563393762
        },
        "44":
        {
            "z": 73.323294005470174,
            "y": 0.0,
            "x": 9.4968292464773363
        },
        "14":
        {
            "z": 0.0,
            "y": 0.0,
            "x": 10.371174563393762
        },
        "34":
        {
            "z": 16.835727419499008,
            "y": 0.0,
            "x": -27.685552802878718
        },
        "24":
        {
            "z": 0.0,
            "y": 0.0,
            "x": -10.371174563393762
        },
        "53":
        {
            "z": 0.0,
            "y": 0.0,
            "x": 31.113523690181285
        },
        "43":
        {
            "z": 73.323294005470174,
            "y": 0.0,
            "x": 9.4968292464773363
        },
        "13":
        {
            "z": 73.323294005470174,
            "y": 0.0,
            "x": -9.4968292464773363
        },
        "33":
        {
            "z": 16.835727419499008,
            "y": 0.0,
            "x": -27.685552802878718
        },
        "23":
        {
            "z": 73.323294005470174,
            "y": 0.0,
            "x": 9.4968292464773363
        }
    },
    "max_node": 53,
    "attributes":
    {
        "name": "Network"
    },
    "dna":
    {
        "z": 0.0,
        "y": 0.0,
        "x": 0.0
    },
    "edge":
    {
        "46":
        {
            "47":
            {
                "data":
                [
                    57.408241024594993,
                    11421.962834231692
                ]
            }
        },
        "16":
        {
            "17":
            {
                "data":
                [
                    112.14442764554572,
                    4521.7087517536411
                ]
            }
        },
        "36":
        {
            "37":
            {
                "data":
                [
                    57.408241024594993,
                    11421.962834231692
                ]
            }
        },
        "26":
        {
            "27":
            {
                "data":
                [
                    112.14442764554572,
                    4521.7087517536411
                ]
            }
        },
        "45":
        {},
        "48":
        {
            "49":
            {
                "data":
                [
                    57.408241024594993,
                    11421.962834231692
                ]
            }
        },
        "15":
        {},
        "18":
        {
            "19":
            {
                "data":
                [
                    112.14442764554572,
                    4521.7087517536411
                ]
            }
        },
        "35":
        {},
        "25":
        {},
        "28":
        {
            "29":
            {
                "data":
                [
                    112.14442764554572,
                    4521.7087517536411
                ]
            }
        },
        "38":
        {
            "39":
            {
                "data":
                [
                    57.408241024594993,
                    11421.962834231692
                ]
            }
        },
        "40":
        {
            "41":
            {
                "data":
                [
                    57.408241024594993,
                    11421.962834231692
                ]
            }
        },
        "50":
        {
            "51":
            {
                "data":
                [
                    57.408241024594993,
                    11421.962834231692
                ]
            }
        },
        "10":
        {
            "11":
            {
                "data":
                [
                    57.408241024594993,
                    11421.962834231692
                ]
            }
        },
        "30":
        {
            "31":
            {
                "data":
                [
                    112.14442764554572,
                    4521.7087517536411
                ]
            }
        },
        "20":
        {
            "21":
            {
                "data":
                [
                    112.14442764554572,
                    4521.7087517536411
                ]
            }
        },
        "47":
        {},
        "17":
        {},
        "37":
        {},
        "27":
        {},
        "52":
        {
            "53":
            {
                "data":
                [
                    57.408241024594993,
                    11421.962834231692
                ]
            }
        },
        "42":
        {
            "43":
            {
                "data":
                [
                    57.408241024594993,
                    11421.962834231692
                ]
            }
        },
        "12":
        {
            "13":
            {
                "data":
                [
                    112.14442764554572,
                    4521.7087517536411
                ]
            }
        },
        "32":
        {
            "33":
            {
                "data":
                [
                    57.408241024594993,
                    11421.962834231692
                ]
            }
        },
        "22":
        {
            "23":
            {
                "data":
                [
                    112.14442764554572,
                    4521.7087517536411
                ]
            }
        },
        "49":
        {},
        "19":
        {},
        "39":
        {},
        "29":
        {},
        "51":
        {},
        "41":
        {},
        "11":
        {},
        "5":
        {},
        "4":
        {
            "5":
            {
                "data":
                [
                    57.408241024594993,
                    11421.962834231692
                ]
            }
        },
        "7":
        {},
        "6":
        {
            "7":
            {
                "data":
                [
                    57.408241024594993,
                    11421.962834231692
                ]
            }
        },
        "1":
        {},
        "0":
        {
            "1":
            {
                "data":
                [
                    57.408241024594993,
                    11421.962834231692
                ]
            }
        },
        "3":
        {},
        "2":
        {
            "3":
            {
                "data":
                [
                    57.408241024594993,
                    11421.962834231692
                ]
            }
        },
        "21":
        {},
        "31":
        {},
        "9":
        {},
        "8":
        {
            "9":
            {
                "data":
                [
                    57.408241024594993,
                    11421.962834231692
                ]
            }
        },
        "44":
        {
            "45":
            {
                "data":
                [
                    57.408241024594993,
                    11421.962834231692
                ]
            }
        },
        "14":
        {
            "15":
            {
                "data":
                [
                    112.14442764554572,
                    4521.7087517536411
                ]
            }
        },
        "34":
        {
            "35":
            {
                "data":
                [
                    57.408241024594993,
                    11421.962834231692
                ]
            }
        },
        "24":
        {
            "25":
            {
                "data":
                [
                    112.14442764554572,
                    4521.7087517536411
                ]
            }
        },
        "53":
        {},
        "43":
        {},
        "13":
        {},
        "33":
        {},
        "23":
        {}
    }
}